silabi_tokenizer/__init__.py
silabi_tokenizer/base_tokenizer.py
silabi_tokenizer/hf_tokenizer.py
silabi_tokenizer/kiswahili_tokenizer.py
silabi_tokenizer/silabi_generator.py
silabi_tokenizer/test.py
silabi_tokenizer-0.5.0.dist-info/LICENSE
silabi_tokenizer-0.5.0.dist-info/METADATA
silabi_tokenizer-0.5.0.dist-info/WHEEL
silabi_tokenizer-0.5.0.dist-info/top_level.txt
silabi_tokenizer-0.5.0.dist-info/RECORD
