Metadata-Version: 2.1
Name: silabi-tokenizer
Version: 0.5.0
Summary: A custom tokenizer for Swahili text using syllabic vocabulary with byte fallback.
Home-page: https://github.com/nguthiru/silabi-tokenizer
Author: Edwin Nguthiru
Author-email: nguthiruedwin@gmail.com
License: MIT
Classifier: Programming Language :: Python :: 3
Classifier: License :: OSI Approved :: MIT License
Classifier: Operating System :: OS Independent
Requires-Python: >=3.6
License-File: LICENSE
Requires-Dist: transformers >=4.0.0
